ctkdlib/__init__.py
ctkdlib/custom_widgets/__init__.py
ctkdlib/custom_widgets/color_wheel.png
ctkdlib/custom_widgets/ctk_calendar.py
ctkdlib/custom_widgets/ctk_chart.py
ctkdlib/custom_widgets/ctk_colorpicker.py
ctkdlib/custom_widgets/ctk_draw.py
ctkdlib/custom_widgets/ctk_gif.py
ctkdlib/custom_widgets/ctk_graph.py
ctkdlib/custom_widgets/ctk_hyperlink.py
ctkdlib/custom_widgets/ctk_meter.py
ctkdlib/custom_widgets/ctk_piechart.py
ctkdlib/custom_widgets/ctk_popupmenu.py
ctkdlib/custom_widgets/ctk_radarchart.py
ctkdlib/custom_widgets/ctk_rangeslider.py
ctkdlib/custom_widgets/ctk_spinbox.py
ctkdlib/custom_widgets/ctk_tooltip.py
ctkdlib/custom_widgets/ctk_video.py
ctkdlib/custom_widgets/ctk_xyframe.py
ctkdlib/custom_widgets/target.png
ctkdlib-8.2.dist-info/licenses/LICENSE.txt
ctkdlib-8.2.dist-info/METADATA
ctkdlib-8.2.dist-info/WHEEL
ctkdlib-8.2.dist-info/dependency_links.txt
ctkdlib-8.2.dist-info/top_level.txt
ctkdlib-8.2.dist-info/RECORD
