Metadata-Version: 2.4
Name: ctkdlib
Version: 8.2
Summary: A special widget library for CTkDesigner
Home-page: https://github.com/Akascape/CTkDesigner
Author: Akash Bora
License: MIT
Keywords: customtkinter,tkinter,ctkdesigner,gui-builder,ui-designer,python-gui-builder
Classifier: License :: OSI Approved :: MIT License
Classifier: Programming Language :: Python :: 3
Classifier: Operating System :: OS Independent
Requires-Python: >=3.6
License-File: LICENSE.txt
Requires-Dist: customtkinter
Requires-Dist: pillow
Dynamic: author
Dynamic: classifier
Dynamic: description
Dynamic: description-content-type
Dynamic: home-page
Dynamic: keywords
Dynamic: license
Dynamic: license-file
Dynamic: requires-dist
Dynamic: requires-python
Dynamic: summary
